OpenHowNet/BabelNetSynset.py
OpenHowNet/Download.py
OpenHowNet/HowNetDict.py
OpenHowNet/Sememe.py
OpenHowNet/Sense.py
OpenHowNet/__init__.py
OpenHowNet/version.py
OpenHowNet-2.0.dist-info/LICENSE
OpenHowNet-2.0.dist-info/METADATA
OpenHowNet-2.0.dist-info/WHEEL
OpenHowNet-2.0.dist-info/top_level.txt
OpenHowNet-2.0.dist-info/RECORD
