Metadata-Version: 2.1
Name: OpenHowNet
Version: 2.0
Summary: OpenHowNet
Home-page: https://github.com/thunlp/OpenHowNet
Author: THUNLP
Author-email: thunlp@gmail.com
License: UNKNOWN
Platform: UNKNOWN
Classifier: Programming Language :: Python :: 3
Classifier: License :: OSI Approved :: MIT License
Classifier: Operating System :: OS Independent
Requires-Python: >=3.6
Requires-Dist: anytree
Requires-Dist: setuptools
Requires-Dist: tqdm
Requires-Dist: requests
